pt_kmeans/__init__.py
pt_kmeans/pt_kmeans.py
pt_kmeans/py.typed
pt_kmeans/version.py
pt_kmeans-0.8.3.dist-info/licenses/LICENSE
pt_kmeans-0.8.3.dist-info/METADATA
pt_kmeans-0.8.3.dist-info/WHEEL
pt_kmeans-0.8.3.dist-info/top_level.txt
pt_kmeans-0.8.3.dist-info/RECORD
