Metadata-Version: 2.4
Name: pt_kmeans
Version: 0.8.3
Summary: K-Means and Hierarchical K-Means implementation in PyTorch
Author: Ofer Hasson
License-Expression: Apache-2.0
Project-URL: Homepage, https://gitlab.com/hassonofer/pt_kmeans
Project-URL: Issues, https://gitlab.com/hassonofer/pt_kmeans/-/issues
Keywords: pytorch,kmeans,clustering,machine-learning,unsupervised-learning,hierarchical-clustering
Classifier: Development Status :: 4 - Beta
Classifier: Intended Audience :: Science/Research
Classifier: Operating System :: OS Independent
Classifier: Programming Language :: Python :: 3
Classifier: Topic :: Scientific/Engineering
Classifier: Topic :: Scientific/Engineering :: Artificial Intelligence
Classifier: Topic :: Software Development
Classifier: Topic :: Software Development :: Libraries
Classifier: Topic :: Software Development :: Libraries :: Python Modules
Requires-Python: >=3.11
License-File: LICENSE
Requires-Dist: numpy>=2.0.0
Requires-Dist: tqdm>=4.60.0
Requires-Dist: torch>=2.4.0
Dynamic: license-file
